AFUNIXSnoopers/__init__.py
afunixsnoopers-1.0.0.dist-info/licenses/LICENSE
afunixsnoopers-1.0.0.dist-info/METADATA
afunixsnoopers-1.0.0.dist-info/WHEEL
afunixsnoopers-1.0.0.dist-info/entry_points.txt
afunixsnoopers-1.0.0.dist-info/top_level.txt
afunixsnoopers-1.0.0.dist-info/RECORD
