Metadata-Version: 2.4
Name: AFUNIXSnoopers
Version: 1.0.0
Summary: Listen on a public UNIX socket and log connections to it
License:                     GNU GENERAL PUBLIC LICENSE
Project-URL: Homepage, https://github.com/jb2170/AFUNIXSnoopers/
License-File: LICENSE
Requires-Dist: ShellContexts
Dynamic: license-file
